[
  {
    "h11": 27,
    "poly_idx": 9192,
    "sm_score": 87,
    "tau_s": 149.99999093217775,
    "ratio": 0.0005604948483753763,
    "V_probe": 138445680.8166047,
    "m32_probe_gev": 17588125434.014656,
    "m32_probe_label": "1.76e+10 GeV",
    "d3_min": -7.0,
    "xi": 0.014538067312880642,
    "W0": 1.0,
    "As": 1.0,
    "gs": 0.1,
    "lvs_results": {
      "ED3 (N_c=1, a_s=2\u03c0)": {
        "a_s": 6.283185307179586,
        "V_LVS": "inf",
        "m32_gev": 0.0,
        "m32_label": "\u226a1 eV (unphysical)",
        "m32_heavy_gev": 0.0
      },
      "SU(2) (a_s=\u03c0)": {
        "a_s": 3.141592653589793,
        "V_LVS": 2.758075800615169e+207,
        "m32_gev": 8.82861884889781e-190,
        "m32_label": "\u226a1 eV (unphysical)",
        "m32_heavy_gev": 1.681084983850161e-293
      },
      "SU(3) (a_s=2\u03c0/3)": {
        "a_s": 2.0943951023931953,
        "V_LVS": 1.1109675415441098e+139,
        "m32_gev": 2.1917832060292654e-121,
        "m32_label": "\u226a1 eV (unphysical)",
        "m32_heavy_gev": 6.575774468304142e-191
      },
      "SU(5) (a_s=2\u03c0/5)": {
        "a_s": 1.2566370614359172,
        "V_LVS": 1.7733798377818516e+84,
        "m32_gev": 1.3730842925595142e-66,
        "m32_label": "\u226a1 eV (unphysical)",
        "m32_heavy_gev": 1.0310893848912698e-108
      },
      "SU(10) (a_s=2\u03c0/10)": {
        "a_s": 0.6283185307179586,
        "V_LVS": 1.038684450139555e+43,
        "m32_gev": 2.3443115949919533e-25,
        "m32_label": "2.34e-13 \u03bceV",
        "m32_heavy_gev": 7.274003749823979e-47
      },
      "SU(20) (a_s=2\u03c0/20)": {
        "a_s": 0.3141592653589793,
        "V_LVS": 1.777499813630534e+22,
        "m32_gev": 0.00013699016907498435,
        "m32_label": "1.37e+02 keV",
        "m32_heavy_gev": 1.0275065990137961e-15
      },
      "SU(30) (a_s=2\u03c0/30)": {
        "a_s": 0.20943951023931953,
        "V_LVS": 1785816979871393.2,
        "m32_gev": 1363.521585608038,
        "m32_label": "1.36e+00 TeV",
        "m32_heavy_gev": 3.2265882174160636e-05
      },
      "SU(50) (a_s=2\u03c0/50)": {
        "a_s": 0.12566370614359174,
        "V_LVS": 3736655955.2079644,
        "m32_gev": 651652180.2351695,
        "m32_label": "6.52e+02 PeV",
        "m32_heavy_gev": 10660.419527673488
      }
    },
    "a_s_for_1TeV": 0.21144317329211393,
    "Nc_for_1TeV": 29.71571609218715,
    "a_s_for_1PeV": 0.16696591275574618,
    "Nc_for_1PeV": 37.63154528655939
  },
  {
    "h11": 27,
    "poly_idx": 45013,
    "sm_score": 85,
    "tau_s": 599.9999999979364,
    "ratio": 0.0009484959210948837,
    "V_probe": 503122424.07765204,
    "m32_probe_gev": 4839776331.702881,
    "m32_probe_label": "4.84e+09 GeV",
    "d3_min": -5.0,
    "xi": 0.014538067312880642,
    "W0": 1.0,
    "As": 1.0,
    "gs": 0.1,
    "lvs_results": {
      "ED3 (N_c=1, a_s=2\u03c0)": {
        "a_s": 6.283185307179586,
        "V_LVS": "inf",
        "m32_gev": 0.0,
        "m32_label": "\u226a1 eV (unphysical)",
        "m32_heavy_gev": 0.0
      },
      "SU(2) (a_s=\u03c0)": {
        "a_s": 3.141592653589793,
        "V_LVS": "inf",
        "m32_gev": 0.0,
        "m32_label": "\u226a1 eV (unphysical)",
        "m32_heavy_gev": 0.0
      },
      "SU(3) (a_s=2\u03c0/3)": {
        "a_s": 2.0943951023931953,
        "V_LVS": "inf",
        "m32_gev": 0.0,
        "m32_label": "\u226a1 eV (unphysical)",
        "m32_heavy_gev": 0.0
      },
      "SU(5) (a_s=2\u03c0/5)": {
        "a_s": 1.2566370614359172,
        "V_LVS": "inf",
        "m32_gev": 0.0,
        "m32_label": "\u226a1 eV (unphysical)",
        "m32_heavy_gev": 0.0
      },
      "SU(10) (a_s=2\u03c0/10)": {
        "a_s": 0.6283185307179586,
        "V_LVS": 1.2923732443033187e+166,
        "m32_gev": 1.884130618405551e-148,
        "m32_label": "\u226a1 eV (unphysical)",
        "m32_heavy_gev": 1.6573606678324298e-231
      },
      "SU(20) (a_s=2\u03c0/20)": {
        "a_s": 0.3141592653589793,
        "V_LVS": 8.867000489710615e+83,
        "m32_gev": 2.7461372115921347e-66,
        "m32_label": "\u226a1 eV (unphysical)",
        "m32_heavy_gev": 2.916311207575783e-108
      },
      "SU(30) (a_s=2\u03c0/30)": {
        "a_s": 0.20943951023931953,
        "V_LVS": 3.0490068260219634e+56,
        "m32_gev": 7.98620711248765e-39,
        "m32_label": "\u226a1 eV (unphysical)",
        "m32_heavy_gev": 4.573633608740746e-67
      },
      "SU(50) (a_s=2\u03c0/50)": {
        "a_s": 0.12566370614359174,
        "V_LVS": 2.7057519844619555e+34,
        "m32_gev": 8.999346628897345e-17,
        "m32_label": "9.00e-05 \u03bceV",
        "m32_heavy_gev": 5.47100343043654e-34
      }
    },
    "a_s_for_1TeV": 0.053981082472335656,
    "Nc_for_1TeV": 116.39605986781771,
    "a_s_for_1PeV": 0.04285292333300915,
    "Nc_for_1PeV": 146.62209292824875
  },
  {
    "h11": 28,
    "poly_idx": 718,
    "sm_score": 82,
    "tau_s": 1749.9999909508042,
    "ratio": 0.008831820551105941,
    "V_probe": 88202666.60657428,
    "m32_probe_gev": 27606875094.39204,
    "m32_probe_label": "2.76e+10 GeV",
    "d3_min": -7.0,
    "xi": 0.014538067312880642,
    "W0": 1.0,
    "As": 1.0,
    "gs": 0.1,
    "lvs_results": {
      "ED3 (N_c=1, a_s=2\u03c0)": {
        "a_s": 6.283185307179586,
        "V_LVS": "inf",
        "m32_gev": 0.0,
        "m32_label": "\u226a1 eV (unphysical)",
        "m32_heavy_gev": 0.0
      },
      "SU(2) (a_s=\u03c0)": {
        "a_s": 3.141592653589793,
        "V_LVS": "inf",
        "m32_gev": 0.0,
        "m32_label": "\u226a1 eV (unphysical)",
        "m32_heavy_gev": 0.0
      },
      "SU(3) (a_s=2\u03c0/3)": {
        "a_s": 2.0943951023931953,
        "V_LVS": "inf",
        "m32_gev": 0.0,
        "m32_label": "\u226a1 eV (unphysical)",
        "m32_heavy_gev": 0.0
      },
      "SU(5) (a_s=2\u03c0/5)": {
        "a_s": 1.2566370614359172,
        "V_LVS": "inf",
        "m32_gev": 0.0,
        "m32_label": "\u226a1 eV (unphysical)",
        "m32_heavy_gev": 0.0
      },
      "SU(10) (a_s=2\u03c0/10)": {
        "a_s": 0.6283185307179586,
        "V_LVS": "inf",
        "m32_gev": 0.0,
        "m32_label": "\u226a1 eV (unphysical)",
        "m32_heavy_gev": 0.0
      },
      "SU(20) (a_s=2\u03c0/20)": {
        "a_s": 0.3141592653589793,
        "V_LVS": 1.2119915387820972e+241,
        "m32_gev": 2.009089933455209e-223,
        "m32_label": "\u226a1 eV (unphysical)",
        "m32_heavy_gev": 0.0
      },
      "SU(30) (a_s=2\u03c0/30)": {
        "a_s": 0.20943951023931953,
        "V_LVS": 2.0834740692952502e+161,
        "m32_gev": 1.1687210490810936e-143,
        "m32_label": "\u226a1 eV (unphysical)",
        "m32_heavy_gev": 2.5604530460344103e-224
      },
      "SU(50) (a_s=2\u03c0/50)": {
        "a_s": 0.12566370614359174,
        "V_LVS": 2.667123749786308e+97,
        "m32_gev": 9.12968511564225e-80,
        "m32_label": "\u226a1 eV (unphysical)",
        "m32_heavy_gev": 1.767804420649323e-128
      }
    },
    "a_s_for_1TeV": 0.01880455069264294,
    "Nc_for_1TeV": 334.1311052775012,
    "a_s_for_1PeV": 0.01498693072070528,
    "Nc_for_1PeV": 419.2443018702299
  },
  {
    "h11": 24,
    "poly_idx": 272,
    "sm_score": 80,
    "tau_s": 199.99999999720603,
    "ratio": 0.002098847044191574,
    "V_probe": 29415335.654071674,
    "m32_probe_gev": 82779949501.03339,
    "m32_probe_label": "8.28e+10 GeV",
    "d3_min": -8.0,
    "xi": 0.014538067312880642,
    "W0": 1.0,
    "As": 1.0,
    "gs": 0.1,
    "lvs_results": {
      "ED3 (N_c=1, a_s=2\u03c0)": {
        "a_s": 6.283185307179586,
        "V_LVS": "inf",
        "m32_gev": 0.0,
        "m32_label": "\u226a1 eV (unphysical)",
        "m32_heavy_gev": 0.0
      },
      "SU(2) (a_s=\u03c0)": {
        "a_s": 3.141592653589793,
        "V_LVS": 5.2711532090759006e+275,
        "m32_gev": 4.619482499213651e-258,
        "m32_label": "\u226a1 eV (unphysical)",
        "m32_heavy_gev": 0.0
      },
      "SU(3) (a_s=2\u03c0/3)": {
        "a_s": 2.0943951023931953,
        "V_LVS": 3.8671479898172825e+184,
        "m32_gev": 6.296629987814484e-167,
        "m32_label": "\u226a1 eV (unphysical)",
        "m32_heavy_gev": 3.2019369603507104e-259
      },
      "SU(5) (a_s=2\u03c0/5)": {
        "a_s": 1.2566370614359172,
        "V_LVS": 3.9701157780347283e+111,
        "m32_gev": 6.133322391936299e-94,
        "m32_label": "\u226a1 eV (unphysical)",
        "m32_heavy_gev": 9.734064228591443e-150
      },
      "SU(10) (a_s=2\u03c0/10)": {
        "a_s": 0.6283185307179586,
        "V_LVS": 5.281034728278235e+56,
        "m32_gev": 4.6108388323245854e-39,
        "m32_label": "\u226a1 eV (unphysical)",
        "m32_heavy_gev": 2.0064134497417096e-67
      },
      "SU(20) (a_s=2\u03c0/20)": {
        "a_s": 0.3141592653589793,
        "V_LVS": 1.3619524689593148e+29,
        "m32_gev": 1.7878744343116572e-11,
        "m32_label": "1.79e+01 \u03bceV",
        "m32_heavy_gev": 4.844578958592038e-26
      },
      "SU(30) (a_s=2\u03c0/30)": {
        "a_s": 0.20943951023931953,
        "V_LVS": 7.281625405961585e+19,
        "m32_gev": 0.03344033597232873,
        "m32_label": "3.34e+01 MeV",
        "m32_heavy_gev": 3.918830372900347e-12
      },
      "SU(50) (a_s=2\u03c0/50)": {
        "a_s": 0.12566370614359174,
        "V_LVS": 2310498531192.216,
        "m32_gev": 1053885.1105624991,
        "m32_label": "1.05e+00 PeV",
        "m32_heavy_gev": 0.6933306834616282
      }
    },
    "a_s_for_1TeV": 0.1592796394623361,
    "Nc_for_1TeV": 39.447510858193105,
    "a_s_for_1PeV": 0.12591609133149345,
    "Nc_for_1PeV": 49.89978040724069
  },
  {
    "h11": 25,
    "poly_idx": 18950,
    "sm_score": 80,
    "tau_s": 799.9999999401334,
    "ratio": 0.0020031700077851973,
    "V_probe": 252381935.55618283,
    "m32_probe_gev": 9648075622.504066,
    "m32_probe_label": "9.65e+09 GeV",
    "d3_min": -9.0,
    "xi": 0.014538067312880642,
    "W0": 1.0,
    "As": 1.0,
    "gs": 0.1,
    "lvs_results": {
      "ED3 (N_c=1, a_s=2\u03c0)": {
        "a_s": 6.283185307179586,
        "V_LVS": "inf",
        "m32_gev": 0.0,
        "m32_label": "\u226a1 eV (unphysical)",
        "m32_heavy_gev": 0.0
      },
      "SU(2) (a_s=\u03c0)": {
        "a_s": 3.141592653589793,
        "V_LVS": "inf",
        "m32_gev": 0.0,
        "m32_label": "\u226a1 eV (unphysical)",
        "m32_heavy_gev": 0.0
      },
      "SU(3) (a_s=2\u03c0/3)": {
        "a_s": 2.0943951023931953,
        "V_LVS": "inf",
        "m32_gev": 0.0,
        "m32_label": "\u226a1 eV (unphysical)",
        "m32_heavy_gev": 0.0
      },
      "SU(5) (a_s=2\u03c0/5)": {
        "a_s": 1.2566370614359172,
        "V_LVS": "inf",
        "m32_gev": 0.0,
        "m32_label": "\u226a1 eV (unphysical)",
        "m32_heavy_gev": 0.0
      },
      "SU(10) (a_s=2\u03c0/10)": {
        "a_s": 0.6283185307179586,
        "V_LVS": 5.609336121982532e+220,
        "m32_gev": 4.340977162087744e-203,
        "m32_label": "\u226a1 eV (unphysical)",
        "m32_heavy_gev": 1.832870447e-313
      },
      "SU(20) (a_s=2\u03c0/20)": {
        "a_s": 0.3141592653589793,
        "V_LVS": 1.9850578585922217e+111,
        "m32_gev": 1.2266644971884456e-93,
        "m32_label": "\u226a1 eV (unphysical)",
        "m32_heavy_gev": 2.7532091931149523e-149
      },
      "SU(30) (a_s=2\u03c0/30)": {
        "a_s": 0.20943951023931953,
        "V_LVS": 5.474096858985441e+74,
        "m32_gev": 4.448222351058835e-57,
        "m32_label": "\u226a1 eV (unphysical)",
        "m32_heavy_gev": 1.9012106971734407e-94
      },
      "SU(50) (a_s=2\u03c0/50)": {
        "a_s": 0.12566370614359174,
        "V_LVS": 2.569024118397486e+45,
        "m32_gev": 9.47830727848095e-28,
        "m32_label": "9.48e-16 \u03bceV",
        "m32_heavy_gev": 1.8700219028293105e-50
      }
    },
    "a_s_for_1TeV": 0.04066023927157385,
    "Nc_for_1TeV": 154.52898014725287,
    "a_s_for_1PeV": 0.03231278001569743,
    "Nc_for_1PeV": 194.44892405194597
  },
  {
    "h11": 25,
    "poly_idx": 38242,
    "sm_score": 80,
    "tau_s": 2755.1797572193027,
    "ratio": 0.00020997413859681602,
    "V_probe": 47530917319.487015,
    "m32_probe_gev": 51229812.87385514,
    "m32_probe_label": "5.12e+01 PeV",
    "d3_min": -5.0,
    "xi": 0.014538067312880642,
    "W0": 1.0,
    "As": 1.0,
    "gs": 0.1,
    "lvs_results": {
      "ED3 (N_c=1, a_s=2\u03c0)": {
        "a_s": 6.283185307179586,
        "V_LVS": "inf",
        "m32_gev": 0.0,
        "m32_label": "\u226a1 eV (unphysical)",
        "m32_heavy_gev": 0.0
      },
      "SU(2) (a_s=\u03c0)": {
        "a_s": 3.141592653589793,
        "V_LVS": "inf",
        "m32_gev": 0.0,
        "m32_label": "\u226a1 eV (unphysical)",
        "m32_heavy_gev": 0.0
      },
      "SU(3) (a_s=2\u03c0/3)": {
        "a_s": 2.0943951023931953,
        "V_LVS": "inf",
        "m32_gev": 0.0,
        "m32_label": "\u226a1 eV (unphysical)",
        "m32_heavy_gev": 0.0
      },
      "SU(5) (a_s=2\u03c0/5)": {
        "a_s": 1.2566370614359172,
        "V_LVS": "inf",
        "m32_gev": 0.0,
        "m32_label": "\u226a1 eV (unphysical)",
        "m32_heavy_gev": 0.0
      },
      "SU(10) (a_s=2\u03c0/10)": {
        "a_s": 0.6283185307179586,
        "V_LVS": "inf",
        "m32_gev": 0.0,
        "m32_label": "\u226a1 eV (unphysical)",
        "m32_heavy_gev": 0.0
      },
      "SU(20) (a_s=2\u03c0/20)": {
        "a_s": 0.3141592653589793,
        "V_LVS": "inf",
        "m32_gev": 0.0,
        "m32_label": "\u226a1 eV (unphysical)",
        "m32_heavy_gev": 0.0
      },
      "SU(30) (a_s=2\u03c0/30)": {
        "a_s": 0.20943951023931953,
        "V_LVS": 7.029282696791069e+252,
        "m32_gev": 3.4640803408171355e-235,
        "m32_label": "\u226a1 eV (unphysical)",
        "m32_heavy_gev": 0.0
      },
      "SU(50) (a_s=2\u03c0/50)": {
        "a_s": 0.12566370614359174,
        "V_LVS": 2.4117888952611853e+152,
        "m32_gev": 1.0096240200725782e-134,
        "m32_label": "\u226a1 eV (unphysical)",
        "m32_heavy_gev": 6.501147638059632e-211
      }
    },
    "a_s_for_1TeV": 0.01202397989488008,
    "Nc_for_1TeV": 522.5545420160777,
    "a_s_for_1PeV": "nan",
    "Nc_for_1PeV": null
  },
  {
    "h11": 26,
    "poly_idx": 30513,
    "sm_score": 80,
    "tau_s": 1399.6504769271287,
    "ratio": 0.00492633130180391,
    "V_probe": 151441175.4026717,
    "m32_probe_gev": 16078850375.569933,
    "m32_probe_label": "1.61e+10 GeV",
    "d3_min": -8.0,
    "xi": 0.014538067312880642,
    "W0": 1.0,
    "As": 1.0,
    "gs": 0.1,
    "lvs_results": {
      "ED3 (N_c=1, a_s=2\u03c0)": {
        "a_s": 6.283185307179586,
        "V_LVS": "inf",
        "m32_gev": 0.0,
        "m32_label": "\u226a1 eV (unphysical)",
        "m32_heavy_gev": 0.0
      },
      "SU(2) (a_s=\u03c0)": {
        "a_s": 3.141592653589793,
        "V_LVS": "inf",
        "m32_gev": 0.0,
        "m32_label": "\u226a1 eV (unphysical)",
        "m32_heavy_gev": 0.0
      },
      "SU(3) (a_s=2\u03c0/3)": {
        "a_s": 2.0943951023931953,
        "V_LVS": "inf",
        "m32_gev": 0.0,
        "m32_label": "\u226a1 eV (unphysical)",
        "m32_heavy_gev": 0.0
      },
      "SU(5) (a_s=2\u03c0/5)": {
        "a_s": 1.2566370614359172,
        "V_LVS": "inf",
        "m32_gev": 0.0,
        "m32_label": "\u226a1 eV (unphysical)",
        "m32_heavy_gev": 0.0
      },
      "SU(10) (a_s=2\u03c0/10)": {
        "a_s": 0.6283185307179586,
        "V_LVS": "inf",
        "m32_gev": 0.0,
        "m32_label": "\u226a1 eV (unphysical)",
        "m32_heavy_gev": 0.0
      },
      "SU(20) (a_s=2\u03c0/20)": {
        "a_s": 0.3141592653589793,
        "V_LVS": 1.7144748216111322e+193,
        "m32_gev": 1.4202599940848203e-175,
        "m32_label": "\u226a1 eV (unphysical)",
        "m32_heavy_gev": 3.430064590838471e-272
      },
      "SU(30) (a_s=2\u03c0/30)": {
        "a_s": 0.20943951023931953,
        "V_LVS": 2.5295273164510488e+129,
        "m32_gev": 9.626304425193275e-112,
        "m32_label": "\u226a1 eV (unphysical)",
        "m32_heavy_gev": 1.913991060182088e-176
      },
      "SU(50) (a_s=2\u03c0/50)": {
        "a_s": 0.12566370614359174,
        "V_LVS": 1.8079659254210544e+78,
        "m32_gev": 1.3468174182723697e-60,
        "m32_label": "\u226a1 eV (unphysical)",
        "m32_heavy_gev": 1.0016444843685374e-99
      }
    },
    "a_s_for_1TeV": 0.023434112196328946,
    "Nc_for_1TeV": 268.1213290497036,
    "a_s_for_1PeV": 0.01866147510849544,
    "Nc_for_1PeV": 336.6928536275909
  },
  {
    "h11": 28,
    "poly_idx": 1937,
    "sm_score": 80,
    "tau_s": 19999.98025226593,
    "ratio": 0.0011884266431282495,
    "V_probe": 69037615189.15318,
    "m32_probe_gev": 35270627.372171655,
    "m32_probe_label": "3.53e+01 PeV",
    "d3_min": -13.0,
    "xi": 0.014538067312880642,
    "W0": 1.0,
    "As": 1.0,
    "gs": 0.1,
    "lvs_results": {
      "ED3 (N_c=1, a_s=2\u03c0)": {
        "a_s": 6.283185307179586,
        "V_LVS": "inf",
        "m32_gev": 0.0,
        "m32_label": "\u226a1 eV (unphysical)",
        "m32_heavy_gev": 0.0
      },
      "SU(2) (a_s=\u03c0)": {
        "a_s": 3.141592653589793,
        "V_LVS": "inf",
        "m32_gev": 0.0,
        "m32_label": "\u226a1 eV (unphysical)",
        "m32_heavy_gev": 0.0
      },
      "SU(3) (a_s=2\u03c0/3)": {
        "a_s": 2.0943951023931953,
        "V_LVS": "inf",
        "m32_gev": 0.0,
        "m32_label": "\u226a1 eV (unphysical)",
        "m32_heavy_gev": 0.0
      },
      "SU(5) (a_s=2\u03c0/5)": {
        "a_s": 1.2566370614359172,
        "V_LVS": "inf",
        "m32_gev": 0.0,
        "m32_label": "\u226a1 eV (unphysical)",
        "m32_heavy_gev": 0.0
      },
      "SU(10) (a_s=2\u03c0/10)": {
        "a_s": 0.6283185307179586,
        "V_LVS": "inf",
        "m32_gev": 0.0,
        "m32_label": "\u226a1 eV (unphysical)",
        "m32_heavy_gev": 0.0
      },
      "SU(20) (a_s=2\u03c0/20)": {
        "a_s": 0.3141592653589793,
        "V_LVS": "inf",
        "m32_gev": 0.0,
        "m32_label": "\u226a1 eV (unphysical)",
        "m32_heavy_gev": 0.0
      },
      "SU(30) (a_s=2\u03c0/30)": {
        "a_s": 0.20943951023931953,
        "V_LVS": "inf",
        "m32_gev": 0.0,
        "m32_label": "\u226a1 eV (unphysical)",
        "m32_heavy_gev": 0.0
      },
      "SU(50) (a_s=2\u03c0/50)": {
        "a_s": 0.12566370614359174,
        "V_LVS": "inf",
        "m32_gev": 0.0,
        "m32_label": "\u226a1 eV (unphysical)",
        "m32_heavy_gev": 0.0
      }
    },
    "a_s_for_1TeV": "nan",
    "Nc_for_1TeV": null,
    "a_s_for_1PeV": "nan",
    "Nc_for_1PeV": null
  }
]